Workbook

Sheet Assumptions
B2: Aegis — ROI & Value Model
B3: Assumptions (edit the yellow input cells)
B4: All figures are ILLUSTRATIVE placeholders — replace with your own data. See 'Notes & Sources'.
B6: Volume & deflection
B7: Annual interaction volume | C7: 500000 | D7: cases/yr | E7: Illustrative. Replace with your contact-center / service-desk volume.
B8: % deflectable to self-service | C8: 0.3 | E8: Share of volume an AI agent can fully self-serve. [ANALYST] range varies widely.
B9: % of remaining handled as agent-assisted | C9: 0.5 | E9: Of non-deflected volume, share where the agent assists a human (time saved).
B11: Unit economics (self-service)
B12: Cost per live / agent-assisted contact | C12: 8.01 | D12: $/contact | E12: [ANALYST] Gartner self-service economics (predecessor SLG evidence base).
B13: Cost per self-service contact | C13: 0.1 | D13: $/contact | E13: [ANALYST] Gartner self-service economics (predecessor SLG evidence base).
B15: Labor productivity
B16: Avg staff minutes saved per assisted case | C16: 6 | D16: min | E16: Illustrative handle-time reduction on agent-assisted cases.
B17: Blended loaded labor cost | C17: 55 | D17: $/hour | E17: Illustrative fully-loaded hourly cost (wages + benefits + overhead).
B19: Token / model cost (Bedrock)
B20: Est. tokens per interaction (in + out) | C20: 4000 | D20: tokens | E20: Illustrative. Depends on prompt size, RAG context, and model.
B21: Blended price per 1,000 tokens | C21: 0.3 | D21: $/1k tok | E21: MODEL ASSUMPTION — set to your chosen Bedrock model's blended in/out price.
B23: Program cost & scale
B24: Number of agents onboarded | C24: 3 | D24: agents | E24: Agents live on the governed platform (chargeback attributes spend per dept).
B25: Annual platform + run cost | C25: 240000 | D25: $/yr | E25: Illustrative Aegis platform + AWS run cost (excl. token/model spend).
B26: One-time implementation cost | C26: 350000 | D26: $ | E26: Illustrative build/engagement cost (connectors, IdP, packs, ATO prep).
B29: Legend:
B30: Yellow / blue = editable input
B31: Black = formula (do not overwrite)
B32: Green = pulled from another sheet

Sheet ROI
B2: ROI Summary
B3: Black = calculated formula. Green = linked from Assumptions. Change inputs on 'Assumptions'.
B5: Derived volumes
B6: Deflected volume (self-service) | C6: =Assumptions!C7*Assumptions!C8 -> 150000 | D6: volume x % deflectable
B7: Assisted volume (human + agent) | C7: =Assumptions!C7*(1-Assumptions!C8)*Assumptions!C9 -> 175000 | D7: remaining x % assisted
B9: Annual benefits
B10: Deflection savings | C10: =C6*(Assumptions!C12-Assumptions!C13) -> 1186500 | D10: deflected x (live - self-service cost)
B11: Labor savings (assisted handle time) | C11: =C7*Assumptions!C16/60*Assumptions!C17 -> 962500 | D11: assisted x min/60 x labor rate
B12: Gross annual benefit | C12: =C10+C11 -> 2149000 | D12: deflection + labor savings
B14: Annual costs
B15: Token / model cost | C15: =Assumptions!C7*Assumptions!C20*Assumptions!C21/1000 -> 600000 | D15: volume x tokens x $/1k / 1000
B16: Platform + run cost | C16: =Assumptions!C25 -> 240000 | D16: from Assumptions
B17: Total annual run cost | C17: =C15+C16 -> 840000 | D17: token + platform
B19: Return
B20: Net annual benefit | C20: =C12-C17 -> 1309000 | D20: gross benefit - total annual cost
B21: Annual ROI % | C21: =IF(C17=0,"n/a",C20/C17) -> 1.5583333 | D21: net annual benefit / total annual cost
B22: Simple payback | C22: =IF(C20<=0,"n/a",Assumptions!C26/(C20/12)) -> 3.2085561 | D22: implementation / net monthly benefit
B23: First-year net (incl. implementation) | C23: =C20-Assumptions!C26 -> 959000 | D23: net annual benefit - one-time implementation
B26: Scenario sensitivity (varying % deflectable)
B27: Scenario | C27: % deflectable | D27: Deflection savings | E27: Labor savings | F27: Gross benefit | G27: Total cost | H27: Net benefit | I27: ROI % | J27: Payback
B28: Conservative | C28: 0.15 | D28: =Assumptions!C7*C28*(Assumptions!C12-Assumptions!C13) -> 593250 | E28: =Assumptions!C7*(1-C28)*Assumptions!C9*Assumptions!C16/60*Assumptions!C17 -> 1168750 | F28: =D28+E28 -> 1762000 | G28: =Assumptions!C7*Assumptions!C20*Assumptions!C21/1000+Assumptions!C25 -> 840000 | H28: =F28-G28 -> 922000 | I28: =IF(G28=0,"n/a",H28/G28) -> 1.097619 | J28: =IF(H28<=0,"n/a",Assumptions!C26/(H28/12)) -> 4.5553145
B29: Base | C29: 0.3 | D29: =Assumptions!C7*C29*(Assumptions!C12-Assumptions!C13) -> 1186500 | E29: =Assumptions!C7*(1-C29)*Assumptions!C9*Assumptions!C16/60*Assumptions!C17 -> 962500 | F29: =D29+E29 -> 2149000 | G29: =Assumptions!C7*Assumptions!C20*Assumptions!C21/1000+Assumptions!C25 -> 840000 | H29: =F29-G29 -> 1309000 | I29: =IF(G29=0,"n/a",H29/G29) -> 1.5583333 | J29: =IF(H29<=0,"n/a",Assumptions!C26/(H29/12)) -> 3.2085561
B30: Aggressive | C30: 0.45 | D30: =Assumptions!C7*C30*(Assumptions!C12-Assumptions!C13) -> 1779750 | E30: =Assumptions!C7*(1-C30)*Assumptions!C9*Assumptions!C16/60*Assumptions!C17 -> 756250 | F30: =D30+E30 -> 2536000 | G30: =Assumptions!C7*Assumptions!C20*Assumptions!C21/1000+Assumptions!C25 -> 840000 | H30: =F30-G30 -> 1696000 | I30: =IF(G30=0,"n/a",H30/G30) -> 2.0190476 | J30: =IF(H30<=0,"n/a",Assumptions!C26/(H30/12)) -> 2.4764151
B31: Base scenario mirrors the summary above. Only % deflectable is varied; edit blue cells to explore.

Sheet Chargeback-Illustration
B2: Per-Department Chargeback (Illustrative)
B3: Bedrock application inference profiles (AIP) tag every call by dept / team / app / data_class.
B4: Cost = tokens x $/1k / 1000, using the blended token price from Assumptions. Replace with CUR data.
B6: Department | C6: Team | D6: Application | E6: Data class | F6: Tokens used (mo) | G6: Inference cost | H6: % of total
B7: Resident Services | C7: 311/CRM | D7: svc-desk-agent | E7: pii | F7: 42000000 | G7: =F7*Assumptions!C21/1000 -> 12600 | H7: =IF($G$11=0,0,G7/$G$11) -> 0.54901961
B8: Health & Human Svcs | C8: Benefits | D8: eligibility-copilot | E8: phi | F8: 18500000 | G8: =F8*Assumptions!C21/1000 -> 5550 | H8: =IF($G$11=0,0,G8/$G$11) -> 0.24183007
B9: Public Safety | C9: Records | D9: cji-lookup-agent | E9: cji | F9: 9800000 | G9: =F9*Assumptions!C21/1000 -> 2940 | H9: =IF($G$11=0,0,G9/$G$11) -> 0.12810458
B10: Finance | C10: Procurement | D10: invoice-triage | E10: pii | F10: 6200000 | G10: =F10*Assumptions!C21/1000 -> 1860 | H10: =IF($G$11=0,0,G10/$G$11) -> 0.081045752
B11: Total | F11: =SUM(F7:F10) -> 76500000 | G11: =SUM(G7:G10) -> 22950 | H11: =IF($G$11=0,0,SUM(H7:H10)) -> 1
B13: Note: token counts are illustrative placeholders. In production, the gateway meter + Cost Explorer/CUR are the financial truth (tags can lag up to 24h).
B14: The gateway enforces hard token caps in real time before spend occurs, so one runaway agent cannot blow the quarter.

Sheet Notes & Sources
B2: Notes, Assumptions & Sources
B4: DISCLAIMER: Every number in this workbook is an ILLUSTRATIVE placeholder for modeling only. It is not a quote, forecast, or guarantee. Replace all yellow input cells with your own validated data before relying on any result. Aegis is a reference platform; it is not yet ATO'd / GovRAMP- or FedRAMP-certified, and "HIPAA-eligible" is not "HIPAA-compliant."
B8: Assumption / figure | C8: Source / tier | D8: Notes
B9: Cost per live / agent-assisted contact ($8.01) | C9: [ANALYST] | D9: Gartner self-service economics via the predecessor SLG evidence base (SOURCES.md §9). Illustrative.
B10: Cost per self-service contact ($0.10) | C10: [ANALYST] | D10: Gartner self-service economics via the predecessor SLG evidence base (SOURCES.md §9). Illustrative.
B11: % deflectable / % assisted | C11: [ANALYST] / customer | D11: Placeholder ranges; must be set from the customer's own workflow and channel mix.
B12: Tokens per interaction | C12: MODEL ASSUMPTION | D12: Depends on prompt size, RAG context, and model; validate against Bedrock invocation logging.
B13: Blended $ per 1,000 tokens | C13: MODEL ASSUMPTION | D13: Set to the chosen Bedrock model's blended in/out price. Not an analyst figure.
B14: Chargeback mechanism | C14: [AWS] | D14: Bedrock application inference profiles + cost-allocation tags -> Cost Explorer / CUR (SOURCES.md §2; docs/05).
B15: Real-time token caps | C15: [AWS] / Aegis | D15: Gateway enforces hard caps before spend; AWS Budgets as account-level backstop (docs/05 §3).
B16: Labor rate / minutes saved | C16: customer | D16: Fully-loaded hourly cost and handle-time reduction are customer-specific; placeholders shown.
B17: Platform / implementation cost | C17: customer / partner | D17: Scoped per engagement (connectors, IdP, packs, ATO prep); see docs/10 RACI.
B19: Evidence tiers:
B20: [AWS] AWS official docs / what's-new / blogs
B21: [GOV] government / regulator / standards body
B22: [ANALYST] analyst or vendor-reported (label illustrative on-slide)
B23: Grounded in the Aegis repo SOURCES.md and docs/05 (FinOps). Gartner self-service economics reused from the predecessor SLG evidence base and remain labeled by tier.
